CzechTVSrt/__init__.py
CzechTVSrt/czechtv.py
CzechTVSrt-0.1.0.dist-info/LICENSE
CzechTVSrt-0.1.0.dist-info/METADATA
CzechTVSrt-0.1.0.dist-info/WHEEL
CzechTVSrt-0.1.0.dist-info/top_level.txt
CzechTVSrt-0.1.0.dist-info/RECORD
