Metadata-Version: 2.1
Name: CzechTVSrt
Version: 0.1.0
Summary: Scraper for Czech TV subtitles.
Home-page: https://github.com/martinbenes1996/CzechTVSrt
Author: Martin Beneš
Author-email: martinbenes1996@gmail.com
License: MIT
Download-URL: https://github.com/martinbenes1996/CzechTVSrt/archive/0.1.0.tar.gz
Keywords: subtitles,titulky,srt,czechia,scraping,webscraping,ivysilani
Platform: UNKNOWN
Classifier: Development Status :: 3 - Alpha
Classifier: Intended Audience :: End Users/Desktop
Classifier: Intended Audience :: Other Audience
Classifier: Natural Language :: Czech
Classifier: Topic :: Internet
Classifier: Topic :: Multimedia
Classifier: Topic :: Multimedia :: Sound/Audio
Classifier: Topic :: Multimedia :: Video
Classifier: Topic :: Text Processing :: Markup :: HTML
Classifier: Topic :: Utilities
Classifier: License :: OSI Approved :: MIT License
Classifier: Programming Language :: Python :: 3
Classifier: Programming Language :: Python :: 3.4
Classifier: Programming Language :: Python :: 3.5
Classifier: Programming Language :: Python :: 3.6
Requires-Dist: bs4
Requires-Dist: requests
